sinopsis_ai/__init__.py
sinopsis_ai/client.py
sinopsis_ai-0.4.0.dist-info/LICENSE
sinopsis_ai-0.4.0.dist-info/METADATA
sinopsis_ai-0.4.0.dist-info/WHEEL
sinopsis_ai-0.4.0.dist-info/top_level.txt
sinopsis_ai-0.4.0.dist-info/RECORD
